lambda_cloud_cli/__init__.py
lambda_cloud_cli/cli.py
lambda_cloud_cli/config.py
lambda_cloud_cli/lambda_api_client.py
lambda_cloud_cli/commands/filesystems.py
lambda_cloud_cli/commands/firewall_cmds.py
lambda_cloud_cli-0.1.36.dist-info/METADATA
lambda_cloud_cli-0.1.36.dist-info/WHEEL
lambda_cloud_cli-0.1.36.dist-info/entry_points.txt
lambda_cloud_cli-0.1.36.dist-info/top_level.txt
lambda_cloud_cli-0.1.36.dist-info/RECORD
